coloured_logger/__init__.py
coloured_logger/logger.py
coloured_logger/logger_config.py
coloured_logger/utils/__init__.py
coloured_logger/utils/clear_handlers.py
coloured_logger-1.0.3.dist-info/LICENSE
coloured_logger-1.0.3.dist-info/METADATA
coloured_logger-1.0.3.dist-info/WHEEL
coloured_logger-1.0.3.dist-info/top_level.txt
coloured_logger-1.0.3.dist-info/RECORD
