Metadata-Version: 2.1
Name: coloured-logger
Version: 1.0.3
Summary: A coloured logger for Python
Home-page: https://github.com/oscar-defelice/coloured-logger
Author: Oscar de Felice
Author-email: oscar.defelice@gmail.com
License: MIT
Keywords: security,scanner
Classifier: Programming Language :: Python :: 3
Classifier: License :: OSI Approved :: MIT License
Classifier: Operating System :: OS Independent
Classifier: Development Status :: 3 - Alpha
Requires-Python: >= 3.9
License-File: LICENSE
